huaweicloudsdkdms/__init__.py
huaweicloudsdkdms/v2/__init__.py
huaweicloudsdkdms/v2/dms_async_client.py
huaweicloudsdkdms/v2/dms_client.py
huaweicloudsdkdms/v2/model/__init__.py
huaweicloudsdkdms/v2/model/batch_create_or_delete_queue_tag_request.py
huaweicloudsdkdms/v2/model/batch_create_or_delete_queue_tag_response.py
huaweicloudsdkdms/v2/model/batch_create_or_delete_tag_req.py
huaweicloudsdkdms/v2/model/batch_create_or_delete_tag_req_tags.py
huaweicloudsdkdms/v2/model/confirm_consumption_messages_req.py
huaweicloudsdkdms/v2/model/confirm_consumption_messages_request.py
huaweicloudsdkdms/v2/model/confirm_consumption_messages_response.py
huaweicloudsdkdms/v2/model/confirm_dead_letters_messages_req.py
huaweicloudsdkdms/v2/model/confirm_dead_letters_messages_request.py
huaweicloudsdkdms/v2/model/confirm_dead_letters_messages_response.py
huaweicloudsdkdms/v2/model/confirm_message_entity.py
huaweicloudsdkdms/v2/model/consume_deadletters_message.py
huaweicloudsdkdms/v2/model/consume_deadletters_message_message.py
huaweicloudsdkdms/v2/model/consume_deadletters_message_request.py
huaweicloudsdkdms/v2/model/consume_deadletters_message_response.py
huaweicloudsdkdms/v2/model/consume_message.py
huaweicloudsdkdms/v2/model/consume_message_message.py
huaweicloudsdkdms/v2/model/consume_messages_request.py
huaweicloudsdkdms/v2/model/consume_messages_response.py
huaweicloudsdkdms/v2/model/create_consumer_group_req.py
huaweicloudsdkdms/v2/model/create_consumer_group_request.py
huaweicloudsdkdms/v2/model/create_consumer_group_resp_groups.py
huaweicloudsdkdms/v2/model/create_consumer_group_response.py
huaweicloudsdkdms/v2/model/create_queue_req.py
huaweicloudsdkdms/v2/model/create_queue_request.py
huaweicloudsdkdms/v2/model/create_queue_response.py
huaweicloudsdkdms/v2/model/delete_queue_request.py
huaweicloudsdkdms/v2/model/delete_queue_response.py
huaweicloudsdkdms/v2/model/delete_specified_consumer_group_request.py
huaweicloudsdkdms-3.1.42.dist-info/LICENSE
huaweicloudsdkdms-3.1.42.dist-info/METADATA
huaweicloudsdkdms-3.1.42.dist-info/WHEEL
huaweicloudsdkdms-3.1.42.dist-info/top_level.txt
huaweicloudsdkdms-3.1.42.dist-info/RECORD
